cupyd/__init__.py
cupyd/core/__init__.py
cupyd/core/etl.py
cupyd/core/exceptions.py
cupyd/core/utils.py
cupyd/core/communication/__init__.py
cupyd/core/communication/connector.py
cupyd/core/communication/counter.py
cupyd/core/communication/event_flag.py
cupyd/core/communication/interruption_handler.py
cupyd/core/computing/__init__.py
cupyd/core/computing/etl_worker.py
cupyd/core/computing/node_worker.py
cupyd/core/constants/__init__.py
cupyd/core/constants/logging.py
cupyd/core/constants/node_actions.py
cupyd/core/constants/sentinel_values.py
cupyd/core/graph/__init__.py
cupyd/core/graph/algorithms.py
cupyd/core/graph/classes.py
cupyd/core/models/__init__.py
cupyd/core/models/etl_segment.py
cupyd/core/models/node_configuration.py
cupyd/core/models/node_exception.py
cupyd/core/nodes/__init__.py
cupyd/core/nodes/bulker.py
cupyd/core/nodes/debulker.py
cupyd/core/nodes/extractor.py
cupyd/core/nodes/filter.py
cupyd/core/nodes/loader.py
cupyd/core/nodes/transformer.py
cupyd/core/stats/__init__.py
cupyd/core/stats/progress_thread.py
cupyd/core/stats/timings_buffer.py
cupyd/core/stats/timings_thread.py
cupyd/examples/__init__.py
cupyd/examples/failed_etl.py
cupyd/examples/readme_etl.py
cupyd/examples/successful_etl.py
cupyd/tests/__init__.py
cupyd/tests/etl/__init__.py
cupyd/tests/etl/nodes.py
cupyd/tests/etl/test_etl.py
cupyd/tests/etl/test_etl_errors.py
cupyd/tests/graph/__init__.py
cupyd/tests/graph/conftest.py
cupyd/tests/graph/test_algorithms.py
cupyd/tests/graph/test_classes.py
cupyd-0.4.0.dist-info/licenses/LICENSE
cupyd-0.4.0.dist-info/METADATA
cupyd-0.4.0.dist-info/WHEEL
cupyd-0.4.0.dist-info/top_level.txt
cupyd-0.4.0.dist-info/RECORD
