Metadata-Version: 2.4
Name: cupyd
Version: 0.4.0
Summary: Python framework to easily build ETLs.
Author-email: Francisco Javier Alonso Rubio <fjalorub@gmail.com>
License: MIT
Project-URL: Repository, https://github.com/jalorub/cupyd.git
Project-URL: Documentation, https://jalorub.github.io/cupyd/
Project-URL: Changelog, https://jalorub.github.io/cupyd/changelog
Keywords: python,data,etl,parallelism,multiprocessing,framework,concurrency,threading
Classifier: Programming Language :: Python :: 3
Classifier: License :: OSI Approved :: MIT License
Classifier: Operating System :: OS Independent
Classifier: Intended Audience :: Developers
Classifier: Topic :: Software Development :: Libraries :: Application Frameworks
Classifier: Development Status :: 3 - Alpha
Requires-Python: >=3.9
License-File: LICENSE
Provides-Extra: docs
Requires-Dist: mkdocs-material; extra == "docs"
Dynamic: license-file
